metaflow_pyinstrument/__init__.py
metaflow_pyinstrument-0.1.1.dist-info/licenses/LICENSE
metaflow_pyinstrument-0.1.1.dist-info/METADATA
metaflow_pyinstrument-0.1.1.dist-info/WHEEL
metaflow_pyinstrument-0.1.1.dist-info/top_level.txt
metaflow_pyinstrument-0.1.1.dist-info/RECORD
