Metadata-Version: 2.4
Name: metaflow-pyinstrument
Version: 0.1.1
Summary: Profile Metaflow steps with pyinstrument and render as HTML cards
License:                                  Apache License
License-File: LICENSE
Requires-Dist: metaflow-card-html
Dynamic: license-file
